ezno_convert/__init__.py
ezno_convert/cli.py
ezno_convert/common.py
ezno_convert/context.py
ezno_convert/convert.py
ezno_convert/enums.py
ezno_convert/gui.py
ezno_convert-0.0.5b4.dist-info/LICENSE
ezno_convert-0.0.5b4.dist-info/METADATA
ezno_convert-0.0.5b4.dist-info/WHEEL
ezno_convert-0.0.5b4.dist-info/entry_points.txt
ezno_convert-0.0.5b4.dist-info/top_level.txt
ezno_convert-0.0.5b4.dist-info/RECORD
