Metadata-Version: 2.1
Name: ezno-convert
Version: 0.0.5b4
Summary: Convert office files quickly and easily through CLI, GUI, or windows explorer context menu
Home-page: https://github.com/ofersadan85/ezno_convert
Author: Ofer Sadan
Author-email: ofersadan85@gmail.com
License: MIT
Platform: UNKNOWN
Classifier: License :: OSI Approved :: MIT License
Classifier: Development Status :: 3 - Alpha
Classifier: Environment :: Console
Classifier: Environment :: Win32 (MS Windows)
Classifier: Intended Audience :: End Users/Desktop
Classifier: Operating System :: Microsoft
Classifier: Operating System :: Microsoft :: Windows
Classifier: Operating System :: Microsoft :: Windows :: Windows 10
Classifier: Programming Language :: Python :: 3
Classifier: Programming Language :: Python :: 3.6
Classifier: Programming Language :: Python :: 3.7
Classifier: Programming Language :: Python :: 3.8
Classifier: Programming Language :: Python :: 3.9
Classifier: Topic :: Desktop Environment :: File Managers
Classifier: Topic :: Office/Business
Classifier: Topic :: Office/Business :: Financial :: Spreadsheet
Classifier: Topic :: Office/Business :: Office Suites
Classifier: Topic :: Printing
Classifier: Topic :: Text Editors :: Word Processors
Classifier: Topic :: Text Processing
Classifier: Topic :: Text Processing :: General
Classifier: Topic :: Utilities
Requires-Python: >=3.6
Requires-Dist: comtypes (>=1.1.8)
Requires-Dist: dataclasses ; python_version < "3.7"
Provides-Extra: gui
Requires-Dist: wxPython (>=4.1.1) ; extra == 'gui'
